sahale/Dockerfile
sahale/__init__.py
sahale/activity_server.py
sahale/app.py
sahale/client.py
sahale/create_activity.py
sahale/fly.toml
sahale/functions.py
sahale/requirements.txt
sahale/sahale_pb2.py
sahale/sahale_pb2.pyi
sahale/sahale_pb2_grpc.py
sahale/start_activity.py
sahale/start_activity_fly.py
sahale-0.0.4.dist-info/METADATA
sahale-0.0.4.dist-info/WHEEL
sahale-0.0.4.dist-info/licenses/LICENSE
sahale-0.0.4.dist-info/RECORD
