Metadata-Version: 2.1
Name: sahale
Version: 0.0.4
Summary: Python sdk for sahale
Project-URL: Homepage, https://github.com/sahaleio/sdk-python
Project-URL: Bug Tracker, https://github.com/sahaleio/sdk-python/issues
Author-email: Jessie Young <jessie@sahale.io>
License-File: LICENSE
Classifier: License :: OSI Approved :: MIT License
Classifier: Operating System :: OS Independent
Classifier: Programming Language :: Python :: 3
Requires-Python: >=3.7
